rustc_t_x64_win_msvc_nightly_p2/__init__.py
rustc_t_x64_win_msvc_nightly_p2/data/rust-lld.exe
rustc_t_x64_win_msvc_nightly_p2-1.91.0.dist-info/METADATA
rustc_t_x64_win_msvc_nightly_p2-1.91.0.dist-info/WHEEL
rustc_t_x64_win_msvc_nightly_p2-1.91.0.dist-info/top_level.txt
rustc_t_x64_win_msvc_nightly_p2-1.91.0.dist-info/RECORD
