Metadata-Version: 2.4
Name: rustc_t_x64_win_msvc_nightly_p2
Version: 1.91.0
Summary: Segment rustc.target.x86_64-pc-windows-msvc part p2
License: MIT
